vsutillib/media/__init__.py
vsutillib/media/mediautils.py
vsutillib/media/classes/__init__.py
vsutillib/media/classes/mediafileinfo.py
vsutillib_media-1.6.2.dist-info/AUTHORS
vsutillib_media-1.6.2.dist-info/LICENSE.txt
vsutillib_media-1.6.2.dist-info/METADATA
vsutillib_media-1.6.2.dist-info/WHEEL
vsutillib_media-1.6.2.dist-info/top_level.txt
vsutillib_media-1.6.2.dist-info/RECORD
