Metadata-Version: 2.1
Name: vsutillib-media
Version: 1.6.2
Summary: vsutillib.media sub package part of vsutillib
Home-page: https://pypi.org/project/vsutillib-media/
Author: Efrain Vergara
Author-email: akai10tsuki@gmail.com
License: MIT
Platform: UNKNOWN
Requires-Python: >=3.8.1, <3.9
Requires-Dist: pymediainfo (>=4.2.1)
